ec2ansible/__init__.py
ec2ansible/cli.py
ec2ansible-0.1.4.dist-info/LICENSE
ec2ansible-0.1.4.dist-info/METADATA
ec2ansible-0.1.4.dist-info/WHEEL
ec2ansible-0.1.4.dist-info/entry_points.txt
ec2ansible-0.1.4.dist-info/top_level.txt
ec2ansible-0.1.4.dist-info/zip-safe
ec2ansible-0.1.4.dist-info/RECORD
