Metadata-Version: 2.1
Name: ec2ansible
Version: 0.1.4
Summary: AWS EC2 inventory generator for Ansible
Home-page: https://github.com/hehachris/ec2ansible
Author: Chris Lam
Author-email: chris@knetgb.com
License: MIT License
Keywords: ansible ec2 aws devops
Platform: UNKNOWN
Requires-Dist: boto
Requires-Dist: six
